Metadata-Version: 1.0
Name: professorerdo-first
Version: 0.1
Summary: Gaussian and Binomial distributions
Home-page: UNKNOWN
Author: Fan Fan
Author-email: mike.fan@foxmail.com
License: UNKNOWN
Platform: UNKNOWN
